Flask_Flash-2.0.0.dist-info/DESCRIPTION.rst
Flask_Flash-2.0.0.dist-info/METADATA
Flask_Flash-2.0.0.dist-info/RECORD
Flask_Flash-2.0.0.dist-info/WHEEL
Flask_Flash-2.0.0.dist-info/metadata.json
Flask_Flash-2.0.0.dist-info/top_level.txt
flask_flash/__init__.py
flask_flash/decorators.py
flask_flash/exceptions.py
flask_flash/extensions.py
flask_flash/flask_sqlalchemy_patch.py
flask_flash/resources.py
flask_flash/utils.py
flask_flash/client/__init__.py
flask_flash/client/agent.py
flask_flash/client/client.py
