Metadata-Version: 1.0
Name: Flask-Flash
Version: 2.0.0
Summary: Flask API framework (API + Client) to create simple APIs from database models.
Home-page: https://github.com/ocervell/flask_flash
Author: Olivier Cervello
Author-email: olivier.cervello@gmail.com
License: UNKNOWN
Platform: UNKNOWN
